CHANGES.txt
LICENSE.txt
MANIFEST.in
README.txt
mpd.py
setup.py
doc/commands.txt
doc/example1.py
doc/example2.py
doc/example3.py
doc/example4.py
python_mpd_twisted.egg-info/PKG-INFO
python_mpd_twisted.egg-info/SOURCES.txt
python_mpd_twisted.egg-info/dependency_links.txt
python_mpd_twisted.egg-info/requires.txt
python_mpd_twisted.egg-info/top_level.txt