Metadata-Version: 1.0
Name: python-mpd-twisted
Version: 0.3.2
Summary: Python MPD client library using Twisted
Home-page: https://code.reaktor42.de/projects/python-mpd-twisted
Author: Oliver Mader
Author-email: b52@reaktor42.de
License: GPL3
Download-URL: http://pypi.python.org/pypi/python-mpd-twisted
Keywords: mpd
Platform: Independent
Classifier: Development Status :: 4 - Beta
Classifier: Intended Audience :: Developers
Classifier: License :: OSI Approved :: GNU General Public License (GPL)
Classifier: Natural Language :: English
Classifier: Operating System :: OS Independent
Classifier: Programming Language :: Python
Classifier: Topic :: Software Development :: Libraries :: Python Modules
